setup.py
TestManager.egg-info/PKG-INFO
TestManager.egg-info/SOURCES.txt
TestManager.egg-info/dependency_links.txt
TestManager.egg-info/entry_points.txt
TestManager.egg-info/requires.txt
TestManager.egg-info/top_level.txt
testmanager/__init__.py
testmanager/api.py
testmanager/labels.py
testmanager/labels_en.py
testmanager/labels_it.py
testmanager/macros.py
testmanager/model.py
testmanager/sql.py
testmanager/stats.py
testmanager/util.py
testmanager/web_ui.py
testmanager/wiki.py
testmanager/workflow.py