Metadata-Version: 1.0
Name: TestManager
Version: 1.2.0
Summary: Test management plugin for Trac
Home-page: http://trac-hacks.org/wiki/TestManagerForTracPlugin
Author: Roberto Longobardi, Marco Cipriani
Author-email: seccanj@gmail.com
License: BSD. See the file LICENSE.txt contained in the package.
Download-URL: https://sourceforge.net/projects/testman4trac/files/
Keywords: trac plugin test case management project quality assurance statistics stats charts charting graph
Platform: UNKNOWN
